data_structure_utils/__init__.py
data_structure_utils/data_structure_utils.py
w_ds_utils-1.0.5.dist-info/METADATA
w_ds_utils-1.0.5.dist-info/WHEEL
w_ds_utils-1.0.5.dist-info/top_level.txt
w_ds_utils-1.0.5.dist-info/RECORD
