Metadata-Version: 2.1
Name: w-ds-utils
Version: 1.0.5
Summary: A light weight command line menu that supports Windows, MacOS, and Linux
Author: kyw
Author-email: 
Keywords: python
Classifier: Development Status :: 1 - Planning
Classifier: Intended Audience :: Developers
Classifier: Programming Language :: Python :: 3
Classifier: Operating System :: Unix
Classifier: Operating System :: MacOS :: MacOS X
Classifier: Operating System :: Microsoft :: Windows
